tkinterdnd2/TkinterDnD.py
tkinterdnd2/__init__.py
tkinterdnd2/tkdnd/linux64/libtkdnd2.9.3.so
tkinterdnd2/tkdnd/linux64/pkgIndex.tcl
tkinterdnd2/tkdnd/linux64/tkdnd.tcl
tkinterdnd2/tkdnd/linux64/tkdnd_compat.tcl
tkinterdnd2/tkdnd/linux64/tkdnd_generic.tcl
tkinterdnd2/tkdnd/linux64/tkdnd_macosx.tcl
tkinterdnd2/tkdnd/linux64/tkdnd_unix.tcl
tkinterdnd2/tkdnd/linux64/tkdnd_utils.tcl
tkinterdnd2/tkdnd/linux64/tkdnd_windows.tcl
tkinterdnd2/tkdnd/osx64/libtkdnd2.9.3.dylib
tkinterdnd2/tkdnd/osx64/pkgIndex.tcl
tkinterdnd2/tkdnd/osx64/tkdnd.tcl
tkinterdnd2/tkdnd/osx64/tkdnd_compat.tcl
tkinterdnd2/tkdnd/osx64/tkdnd_generic.tcl
tkinterdnd2/tkdnd/osx64/tkdnd_macosx.tcl
tkinterdnd2/tkdnd/osx64/tkdnd_unix.tcl
tkinterdnd2/tkdnd/osx64/tkdnd_utils.tcl
tkinterdnd2/tkdnd/osx64/tkdnd_windows.tcl
tkinterdnd2/tkdnd/win64/libtkdnd2.9.3.dll
tkinterdnd2/tkdnd/win64/pkgIndex.tcl
tkinterdnd2/tkdnd/win64/tkdnd.tcl
tkinterdnd2/tkdnd/win64/tkdnd2.9.3.lib
tkinterdnd2/tkdnd/win64/tkdnd_compat.tcl
tkinterdnd2/tkdnd/win64/tkdnd_generic.tcl
tkinterdnd2/tkdnd/win64/tkdnd_macosx.tcl
tkinterdnd2/tkdnd/win64/tkdnd_unix.tcl
tkinterdnd2/tkdnd/win64/tkdnd_utils.tcl
tkinterdnd2/tkdnd/win64/tkdnd_windows.tcl
tkinterdnd2_osxarm64-1.1.0.dist-info/LICENSE
tkinterdnd2_osxarm64-1.1.0.dist-info/METADATA
tkinterdnd2_osxarm64-1.1.0.dist-info/WHEEL
tkinterdnd2_osxarm64-1.1.0.dist-info/top_level.txt
tkinterdnd2_osxarm64-1.1.0.dist-info/RECORD
