Metadata-Version: 2.1
Name: tkinterdnd2-osxarm64
Version: 1.1.0
Summary: TkinterDnD2 is a python wrapper for George Petasis'' tkDnD Tk extension version 2
Home-page: https://github.com/blacklein/tkinterdnd2-osxarm64
Author: petasis\pmgagne\eliav2\blacklein
Classifier: Development Status :: 2 - Pre-Alpha
Classifier: Programming Language :: Python :: 3
Classifier: License :: OSI Approved :: MIT License
Requires-Python: >=3.6
License-File: LICENSE
